libgeosuitesnd/__init__.py
libgeosuitesnd/flags.csv
libgeosuitesnd/methods.csv
libgeosuitesnd/stop_reasons.csv
multilibgeosuitesnd-0.0.10.1.dist-info/licenses/LICENSE
multilibgeosuitesnd-0.0.10.1.dist-info/METADATA
multilibgeosuitesnd-0.0.10.1.dist-info/WHEEL
multilibgeosuitesnd-0.0.10.1.dist-info/entry_points.txt
multilibgeosuitesnd-0.0.10.1.dist-info/top_level.txt
multilibgeosuitesnd-0.0.10.1.dist-info/RECORD
